{
    "hands_on_practices": [
        {
            "introduction": "让我们从 Gilbert-Varshamov (GV) 界的一个最基础的应用开始：计算给定参数下一个二进制码至少能保证的码字数量。这个练习将帮助你熟悉 GV 界的公式，并理解二项式系数 $ \\binom{n}{i} $ 在定义汉明球“体积”时所扮演的角色。这是掌握 GV 界所能提供存在性保证的第一步。",
            "id": "1626825",
            "problem": "在编码理论领域，一个基本目标是构造既能有效利用比特又对传输错误具有鲁棒性的纠错码。码的大小，即其包含的唯一码字的数量，是衡量其效率的一个关键指标。对于一个码字长度为 $n$、最小汉明距离为 $d$ 的二进制码（其中码字是0和1组成的字符串），其可能的最大大小由函数 $A_2(n,d)$ 表示。\n\nGilbert-Varshamov (GV) 界提供了一个强大的存在性结果，为这类码确定了一个保证的最小大小。该界表明，存在一个长度为 $n$、最小距离为 $d$ 的二进制码，其大小 $M$ 满足以下不等式：\n$$M \\ge \\frac{2^n}{\\sum_{i=0}^{d-1} \\binom{n}{i}}$$\n此处，$\\binom{n}{i}$ 代表二项式系数，用于计算从一个包含 $n$ 个元素的集合中选取 $i$ 个元素的方式数量。\n\n您的任务是为一个新的数据存储系统评估一个潜在码的属性。该系统需要一个码字长度为 $n=10$、最小汉明距离为 $d=3$ 的二进制码。\n\n请使用所提供的 Gilbert-Varshamov 界公式，确定这样一个码保证拥有的码字数量的最小整数值。",
            "solution": "我们应用 Gilbert-Varshamov 界，该界表明对于一个长度为 $n$、最小汉明距离为 $d$ 的二进制码，存在一个大小为 $M$ 的码满足\n$$\nM \\ge \\frac{2^{n}}{\\sum_{i=0}^{d-1} \\binom{n}{i}}.\n$$\n代入 $n=10$ 和 $d=3$：\n$$\nM \\ge \\frac{2^{10}}{\\binom{10}{0}+\\binom{10}{1}+\\binom{10}{2}}.\n$$\n显式地计算二项式系数：\n$$\n\\binom{10}{0}=1,\\quad \\binom{10}{1}=10,\\quad \\binom{10}{2}=\\frac{10\\cdot 9}{2}=45,\n$$\n所以分母是\n$$\n1+10+45=56.\n$$\n分子是\n$$\n2^{10}=1024.\n$$\n因此，\n$$\nM \\ge \\frac{1024}{56}=\\frac{256}{14}=\\frac{128}{7}.\n$$\n由于码字数量 $M$ 必须是一个整数，满足该不等式的最小整数是\n$$\n\\left\\lceil \\frac{128}{7} \\right\\rceil=19.\n$$\n因此，由 Gilbert-Varshamov 界保证的最小整数值是 $19$。",
            "answer": "$$\\boxed{19}$$"
        },
        {
            "introduction": "在掌握了基本计算后，我们将视角从分析转向设计。在许多现实世界的应用中，我们通常预先知道需要编码的信息数量（码字数量 $M$）以及期望的纠错能力（最小距离 $d$）。这个练习将问题反转，要求你确定满足这些需求的最小码长 $n$。这个过程展示了 GV 界如何在纠错码的初步设计阶段成为一个至关重要的工具。",
            "id": "1626823",
            "problem": "一名研究生正在为一个小型数据传输实验设计一个二元纠错码。该码需要能表示至少 $M=12$ 个不同的消息。为确保抗噪声的鲁棒性，任意两个不同码字之间的最小汉明距离必须设计为 $d=3$。\n\n该学生从信息论课上回忆起 Gilbert-Varshamov 界，该界保证了如果满足以下条件，就存在一个码长为 $n$、大小为 $M$、最小距离为 $d$ 的二元码：\n$$ M \\left( \\sum_{i=0}^{d-1} \\binom{n}{i} \\right) \\le 2^n $$\n其中 $\\binom{n}{i}$ 是二项式系数“n 选 i”。\n\n该学生希望使用尽可能短的码长以最小化传输开销。能够使 Gilbert-Varshamov 界保证这种码存在的最小整数码长 $n$ 是多少？",
            "solution": "我们应用二元码的 Gilbert-Varshamov 界，该界保证码存在的条件是\n$$\nM \\left( \\sum_{i=0}^{d-1} \\binom{n}{i} \\right) \\le 2^{n}.\n$$\n当 $M=12$ 且 $d=3$ 时，我们有\n$$\n\\sum_{i=0}^{2} \\binom{n}{i} = \\binom{n}{0} + \\binom{n}{1} + \\binom{n}{2} = 1 + n + \\frac{n(n-1)}{2}.\n$$\n因此条件变为\n$$\n12\\left(1 + n + \\frac{n(n-1)}{2}\\right) \\le 2^{n}.\n$$\n化简左边，\n$$\n1 + n + \\frac{n(n-1)}{2} = \\frac{n^{2} + n + 2}{2},\n$$\n所以不等式为\n$$\n6\\left(n^{2} + n + 2\\right) \\le 2^{n}.\n$$\n我们寻找满足此条件的最小整数 $n$。对递增的 $n$ 计算不等式两边的值：\n$$\nn=1:\\quad 6(1^{2}+1+2)=24,\\quad 2^{1}=2 \\quad\\Rightarrow\\quad 24 \\nleq 2,\n$$\n$$\nn=2:\\quad 6(4+2+2)=48,\\quad 2^{2}=4 \\quad\\Rightarrow\\quad 48 \\nleq 4,\n$$\n$$\nn=3:\\quad 6(9+3+2)=84,\\quad 2^{3}=8 \\quad\\Rightarrow\\quad 84 \\nleq 8,\n$$\n$$\nn=4:\\quad 6(16+4+2)=132,\\quad 2^{4}=16 \\quad\\Rightarrow\\quad 132 \\nleq 16,\n$$\n$$\nn=5:\\quad 6(25+5+2)=192,\\quad 2^{5}=32 \\quad\\Rightarrow\\quad 192 \\nleq 32,\n$$\n$$\nn=6:\\quad 6(36+6+2)=264,\\quad 2^{6}=64 \\quad\\Rightarrow\\quad 264 \\nleq 64,\n$$\n$$\nn=7:\\quad 6(49+7+2)=348,\\quad 2^{7}=128 \\quad\\Rightarrow\\quad 348 \\nleq 128,\n$$\n$$\nn=8:\\quad 6(64+8+2)=444,\\quad 2^{8}=256 \\quad\\Rightarrow\\quad 444 \\nleq 256,\n$$\n$$\nn=9:\\quad 6(81+9+2)=552,\\quad 2^{9}=512 \\quad\\Rightarrow\\quad 552 \\nleq 512,\n$$\n$$\nn=10:\\quad 6(100+10+2)=672,\\quad 2^{10}=1024 \\quad\\Rightarrow\\quad 672 \\le 1024.\n$$\n因此，该界保证码存在的最小码长 $n$ 是 $n=10$。",
            "answer": "$$\\boxed{10}$$"
        },
        {
            "introduction": "现在，我们将前一个练习中的设计原理应用到一个更复杂、更贴近现实的场景——为深空探测器设计存储系统。这个问题要求你处理更大的数值，并进一步巩固寻找合适码长的迭代过程。该问题的背景设定也强调了 GV 界的构造性证明（即贪心算法）与实际编码设计之间的深刻联系。",
            "id": "1626831",
            "problem": "在编码理论中，对于给定的码字长度 $n$ 和最小汉明距离 $d$，寻找二进制码的最大可能大小（记为 $A_2(n,d)$）是一个核心且困难的问题。这个优化问题可以被表述为一个整数线性规划 (ILP)。设所有长度为 $n$ 的二进制码字的集合为 $V = \\{0,1\\}^n$。对于每个码字 $v \\in V$，我们引入一个二进制决策变量 $x_v$，当 $v$ 被包含在我们的码中时，$x_v = 1$，否则 $x_v = 0$。那么，寻找最大可能码的问题等价于以下整数线性规划：\n\n最大化：\n$$ \\sum_{v \\in V} x_v $$\n约束条件：\n$$ x_u + x_v \\le 1 \\quad \\text{for all pairs } u, v \\in V \\text{ where } 1 \\le d_H(u,v) < d $$\n$$ x_v \\in \\{0,1\\} \\quad \\text{for all } v \\in V $$\n这里，$d_H(u,v)$ 表示码字 $u$ 和 $v$ 之间的汉明距离。\n\n对于非平凡的 $n$，求解这个整数线性规划在计算上是难解的。然而，一个简单的贪心算法可以用来构造一个有效的码。该算法流程如下：\n1. 从一个空码 $C = \\emptyset$ 开始。\n2. 从 $V$ 中任选一个码字并将其添加到 $C$ 中。\n3. 重复寻找一个码字 $w \\in V$，使得对于所有已在 $C$ 中的码字 $c$，都满足条件 $d_H(w,c) \\ge d$。将 $w$ 添加到 $C$ 中。\n4. 当找不到这样的码字 $w$ 时，算法终止。\n\n这个贪心构造过程保证了存在一个达到特定最小规模的码。这个结果被称为 Gilbert-Varshamov (GV) 界，它表明保证存在一个大小至少为 $M$ 的码，其中\n$$ M = \\frac{2^n}{\\sum_{i=0}^{d-1} \\binom{n}{i}} $$\n\n一个工程师团队正在为一台深空探测器设计内存系统。该系统必须存储至少 4096 个唯一的操作指令。为确保数据在宇宙射线干扰下的完整性，他们决定使用一种能够纠正存储指令中任意两个比特翻转的纠错码。一个最小汉明距离为 $d$ 的码最多可以纠正 $\\lfloor (d-1)/2 \\rfloor$ 个错误。这个要求将他们的最小汉明距离设定为 $d=5$。\n\n使用 Gilbert-Varshamov 界，确定保证该应用存在合适码的最小整数码长 $n$。",
            "solution": "问题要求解出能够支持一个至少包含 $M_{req} = 4096$ 个码字且最小汉明距离为 $d=5$ 的码的最小整数码长 $n$。Gilbert-Varshamov (GV) 界保证了存在一个大小至少为 $M_{GV}$ 的码，其中\n$$ M_{GV} = \\frac{2^n}{\\sum_{i=0}^{d-1} \\binom{n}{i}} $$\n为了找到所需的 $n$，我们必须找到使保证大小 $M_{GV}$ 大于或等于所需大小 $M_{req}$ 的最小整数 $n$。\n条件是 $M_{GV} \\ge M_{req}$。\n\n代入给定值 $M_{req} = 4096$ 和 $d=5$，我们得到不等式：\n$$ \\frac{2^n}{\\sum_{i=0}^{5-1} \\binom{n}{i}} \\ge 4096 $$\n$$ \\frac{2^n}{\\sum_{i=0}^{4} \\binom{n}{i}} \\ge 4096 $$\n\n我们可以将其重写为：\n$$ 2^n \\ge 4096 \\cdot \\left( \\sum_{i=0}^{4} \\binom{n}{i} \\right) $$\n我们展开求和项，它表示在维度为 $n$ 的空间中半径为 4 的汉明球的体积：\n$$ V(n,4) = \\sum_{i=0}^{4} \\binom{n}{i} = \\binom{n}{0} + \\binom{n}{1} + \\binom{n}{2} + \\binom{n}{3} + \\binom{n}{4} $$\n二项式系数的表达式为 $\\binom{n}{k} = \\frac{n!}{k!(n-k)!}$。\n$$ V(n,4) = 1 + n + \\frac{n(n-1)}{2} + \\frac{n(n-1)(n-2)}{6} + \\frac{n(n-1)(n-2)(n-3)}{24} $$\n我们需要求解的关于最小整数 $n$ 的不等式是：\n$$ 2^n \\ge 4096 \\cdot V(n,4) $$\n这个不等式无法解析地求解 $n$。我们必须通过测试 $n$ 的整数值来找到满足条件的最小值。不等式的左边随 $n$呈指数增长，而右边呈多项式增长（$n^4$ 级别）。我们预计存在一个解。我们开始测试数值。一个合理的起点是选择一个比 $\\log_2(4096)=12$ 稍大的 $n$。\n\n我们测试 $n=26$。\n首先，我们计算汉明球的体积 $V(26,4)$：\n$$ \\binom{26}{0} = 1 $$\n$$ \\binom{26}{1} = 26 $$\n$$ \\binom{26}{2} = \\frac{26 \\times 25}{2} = 325 $$\n$$ \\binom{26}{3} = \\frac{26 \\times 25 \\times 24}{3 \\times 2 \\times 1} = 2600 $$\n$$ \\binom{26}{4} = \\frac{26 \\times 25 \\times 24 \\times 23}{4 \\times 3 \\times 2 \\times 1} = 14950 $$\n$$ V(26,4) = 1 + 26 + 325 + 2600 + 14950 = 17902 $$\n现在我们检验 $n=26$ 时不等式是否成立：\n不等式左侧 (LHS)：$2^{26} = 67,108,864$。\n不等式右侧 (RHS)：$4096 \\times V(26,4) = 4096 \\times 17902 = 73,326,592$。\n条件是 $67,108,864 \\ge 73,326,592$，这是不成立的。所以，$n=26$ 不够大。\n\n我们测试下一个整数，$n=27$。\n首先，我们计算汉明球的体积 $V(27,4)$：\n$$ \\binom{27}{0} = 1 $$\n$$ \\binom{27}{1} = 27 $$\n$$ \\binom{27}{2} = \\frac{27 \\times 26}{2} = 351 $$\n$$ \\binom{27}{3} = \\frac{27 \\times 26 \\times 25}{3 \\times 2 \\times 1} = 2925 $$\n$$ \\binom{27}{4} = \\frac{27 \\times 26 \\times 25 \\times 24}{4 \\times 3 \\times 2 \\times 1} = 17550 $$\n$$ V(27,4) = 1 + 27 + 351 + 2925 + 17550 = 20854 $$\n现在我们检验 $n=27$ 时不等式是否成立：\n不等式左侧 (LHS)：$2^{27} = 134,217,728$。\n不等式右侧 (RHS)：$4096 \\times V(27,4) = 4096 \\times 20854 = 85,417,472$。\n条件是 $134,217,728 \\ge 85,417,472$，这是成立的。所以，$n=27$ 是一个可能的码长。\n\n由于不等式在 $n=26$ 时不成立，而在 $n=27$ 时成立，因此由 Gilbert-Varshamov 界保证存在所需码的最小整数码长是 $n=27$。",
            "answer": "$$\\boxed{27}$$"
        }
    ]
}